[
  {
    "id": 32788,
    "subject": "history",
    "exam_type": "JAMB",
    "exam_year": "2010",
    "question": "The savannah region of Nigeria is\ncharacterized by",
    "options": {
      "A": "sparse vegetation",
      "B": "high population density",
      "C": "abundant resources",
      "D": "large bodies of water."
    },
    "image_url": "",
    "image_cloudinary": "",
    "correct_answer": "A",
    "explanation": "click here",
    "explanation_image_url": "",
    "explanation_image_cloudinary": "",
    "url": "https://myschool.ng/classroom/history/32788",
    "passage": ""
  },
  {
    "id": 32789,
    "subject": "history",
    "exam_type": "JAMB",
    "exam_year": "2010",
    "question": "A major economic activity among the Nupe was",
    "options": {
      "A": "horse breeding",
      "B": "leather work",
      "C": "canoe-building",
      "D": "cattle rearing."
    },
    "image_url": "",
    "image_cloudinary": "",
    "correct_answer": "B",
    "explanation": "click here",
    "explanation_image_url": "",
    "explanation_image_cloudinary": "",
    "url": "https://myschool.ng/classroom/history/32789",
    "passage": ""
  },
  {
    "id": 32790,
    "subject": "history",
    "exam_type": "JAMB",
    "exam_year": "2010",
    "question": "The main features of the economy of the forest zone of Nigeria in the eighteenth century were",
    "options": {
      "A": "pastoral farming and fishing",
      "B": "fishing and salt-making",
      "C": "cotton cultivation and weaving",
      "D": "cash crop production and trading."
    },
    "image_url": "",
    "image_cloudinary": "",
    "correct_answer": "B",
    "explanation": "click here",
    "explanation_image_url": "",
    "explanation_image_cloudinary": "",
    "url": "https://myschool.ng/classroom/history/32790",
    "passage": ""
  },
  {
    "id": 32791,
    "subject": "history",
    "exam_type": "JAMB",
    "exam_year": "2010",
    "question": "The spread of Islam between the 11th and 14th centuries in Nigeria was largely due to",
    "options": {
      "A": "Arab missionary activities",
      "B": "the waging of jihads",
      "C": "trade and commerce",
      "D": "absence of any religion in the area."
    },
    "image_url": "",
    "image_cloudinary": "",
    "correct_answer": "C",
    "explanation": "click here",
    "explanation_image_url": "",
    "explanation_image_cloudinary": "",
    "url": "https://myschool.ng/classroom/history/32791",
    "passage": ""
  },
  {
    "id": 32792,
    "subject": "history",
    "exam_type": "JAMB",
    "exam_year": "2010",
    "question": "A significant effect of the Christian missionary activity in Nigeria was the",
    "options": {
      "A": "introduction of formal education",
      "B": "training of nationalists",
      "C": "introduction of new crops",
      "D": "abolition of the slave trade."
    },
    "image_url": "",
    "image_cloudinary": "",
    "correct_answer": "A",
    "explanation": "click here",
    "explanation_image_url": "",
    "explanation_image_cloudinary": "",
    "url": "https://myschool.ng/classroom/history/32792",
    "passage": ""
  },
  {
    "id": 32793,
    "subject": "history",
    "exam_type": "JAMB",
    "exam_year": "2010",
    "question": "An outstanding reason for the abolition of the trans-Atlantic slave trade was",
    "options": {
      "A": "industrial revolution",
      "B": "nationalist agitation",
      "C": "legitimate trade",
      "D": "railway construction."
    },
    "image_url": "",
    "image_cloudinary": "",
    "correct_answer": "A",
    "explanation": "click here",
    "explanation_image_url": "",
    "explanation_image_cloudinary": "",
    "url": "https://myschool.ng/classroom/history/32793",
    "passage": ""
  },
  {
    "id": 32794,
    "subject": "history",
    "exam_type": "JAMB",
    "exam_year": "2010",
    "question": "A major factor that led to the success of the Sokoto jihad was",
    "options": {
      "A": "military assistance from Borno",
      "B": "lack of unity among the Hausa states",
      "C": "the use of fire-arms by the jihadists",
      "D": "periodic divine interventions."
    },
    "image_url": "",
    "image_cloudinary": "",
    "correct_answer": "B",
    "explanation": "click here",
    "explanation_image_url": "",
    "explanation_image_cloudinary": "",
    "url": "https://myschool.ng/classroom/history/32794",
    "passage": ""
  },
  {
    "id": 32795,
    "subject": "history",
    "exam_type": "JAMB",
    "exam_year": "2010",
    "question": "Which of the following was a part of the Sokoto Caliphate?",
    "options": {
      "A": "Kukawa.",
      "B": "Yauri.",
      "C": "Biu.",
      "D": "Lokoja."
    },
    "image_url": "",
    "image_cloudinary": "",
    "correct_answer": "B",
    "explanation": "click here",
    "explanation_image_url": "",
    "explanation_image_cloudinary": "",
    "url": "https://myschool.ng/classroom/history/32795",
    "passage": ""
  },
  {
    "id": 32796,
    "subject": "history",
    "exam_type": "JAMB",
    "exam_year": "2010",
    "question": "The legendary founder of the Kanuri was",
    "options": {
      "A": "Ali Ghaji",
      "B": "Idris b. Ali Katagarmabe",
      "C": "Idris Alooma",
      "D": "Sayf b. dhi Yazan."
    },
    "image_url": "",
    "image_cloudinary": "",
    "correct_answer": "A",
    "explanation": "click here",
    "explanation_image_url": "",
    "explanation_image_cloudinary": "",
    "url": "https://myschool.ng/classroom/history/32796",
    "passage": ""
  },
  {
    "id": 32798,
    "subject": "history",
    "exam_type": "JAMB",
    "exam_year": "2010",
    "question": "The Queen mother, Magira, played a prominent role in the government of the",
    "options": {
      "A": "Hausa States",
      "B": "Kwararafa Kingdom",
      "C": "Kanem Borno Empire",
      "D": "Igala Kingdom."
    },
    "image_url": "",
    "image_cloudinary": "",
    "correct_answer": "C",
    "explanation": "click here",
    "explanation_image_url": "",
    "explanation_image_cloudinary": "",
    "url": "https://myschool.ng/classroom/history/32798",
    "passage": ""
  },
  {
    "id": 32799,
    "subject": "history",
    "exam_type": "JAMB",
    "exam_year": "2010",
    "question": "The Ekiti Parapo was an alliance against",
    "options": {
      "A": "the Muslim incursion into Yorubaland",
      "B": "the rising power of Ibadan",
      "C": "Christian missionary presence in Yorubaland",
      "D": "the abolition of the slave trade."
    },
    "image_url": "",
    "image_cloudinary": "",
    "correct_answer": "B",
    "explanation": "click here",
    "explanation_image_url": "",
    "explanation_image_cloudinary": "",
    "url": "https://myschool.ng/classroom/history/32799",
    "passage": ""
  },
  {
    "id": 32800,
    "subject": "history",
    "exam_type": "JAMB",
    "exam_year": "2010",
    "question": "The Oyo Empire collapsed as a result of",
    "options": {
      "A": "internal and external crises",
      "B": "the revolt of Afonja",
      "C": "the weakening of the army",
      "D": "British presence in Yorubaland."
    },
    "image_url": "",
    "image_cloudinary": "",
    "correct_answer": "A",
    "explanation": "click here",
    "explanation_image_url": "",
    "explanation_image_cloudinary": "",
    "url": "https://myschool.ng/classroom/history/32800",
    "passage": ""
  },
  {
    "id": 32802,
    "subject": "history",
    "exam_type": "JAMB",
    "exam_year": "2010",
    "question": "The failure of the Ogiso dynasty in Benin was attributed to",
    "options": {
      "A": "weakness and dependence of the rulers",
      "B": "peoples’ resentment against the system",
      "C": "the declining economy of the state",
      "D": "inadequate supply of arms and ammunition."
    },
    "image_url": "",
    "image_cloudinary": "",
    "correct_answer": "A",
    "explanation": "click here",
    "explanation_image_url": "",
    "explanation_image_cloudinary": "",
    "url": "https://myschool.ng/classroom/history/32802",
    "passage": ""
  },
  {
    "id": 32803,
    "subject": "history",
    "exam_type": "JAMB",
    "exam_year": "2010",
    "question": "The greatest ruler in the history of Benin Kingdom was",
    "options": {
      "A": "Oba Ewuare",
      "B": "Oba Ewedo",
      "C": "Oba Ovonramwen",
      "D": "Oba Ewuakpe."
    },
    "image_url": "",
    "image_cloudinary": "",
    "correct_answer": "A",
    "explanation": "click here",
    "explanation_image_url": "",
    "explanation_image_cloudinary": "",
    "url": "https://myschool.ng/classroom/history/32803",
    "passage": ""
  },
  {
    "id": 32804,
    "subject": "history",
    "exam_type": "JAMB",
    "exam_year": "2010",
    "question": "Armed resistance to British rule in Northern Nigeria ended with the conquest of",
    "options": {
      "A": "Kano and Sokoto",
      "B": "Bida and Kano",
      "C": "Katsina and Kano",
      "D": "Bauchi and Katsina."
    },
    "image_url": "",
    "image_cloudinary": "",
    "correct_answer": "A",
    "explanation": "click here",
    "explanation_image_url": "",
    "explanation_image_cloudinary": "",
    "url": "https://myschool.ng/classroom/history/32804",
    "passage": ""
  },
  {
    "id": 32805,
    "subject": "history",
    "exam_type": "JAMB",
    "exam_year": "2010",
    "question": "The Colony and Protectorate of Lagos was amalgameted with the Protectorate of Southern Nigeria in 1906 to form the",
    "options": {
      "A": "Colony and Protectorate of Southern Nigeria",
      "B": "Colony and Protectorate of Nigeria",
      "C": "Protectorate of Southern Nigeria",
      "D": "Oil Rivers Protectorate."
    },
    "image_url": "",
    "image_cloudinary": "",
    "correct_answer": "A",
    "explanation": "click here",
    "explanation_image_url": "",
    "explanation_image_cloudinary": "",
    "url": "https://myschool.ng/classroom/history/32805",
    "passage": ""
  },
  {
    "id": 32807,
    "subject": "history",
    "exam_type": "JAMB",
    "exam_year": "2010",
    "question": "A reason for the amalgamation of the Northern and Southern protectorates of Nigeria in 1914 was",
    "options": {
      "A": "economic expediency",
      "B": "territorial integration",
      "C": "political balancing",
      "D": "religious harmony."
    },
    "image_url": "",
    "image_cloudinary": "",
    "correct_answer": "A",
    "explanation": "click here",
    "explanation_image_url": "",
    "explanation_image_cloudinary": "",
    "url": "https://myschool.ng/classroom/history/32807",
    "passage": ""
  },
  {
    "id": 32808,
    "subject": "history",
    "exam_type": "JAMB",
    "exam_year": "2010",
    "question": "The Nigerian Council established in 1914 was ineffective because it",
    "options": {
      "A": "was not designed to be so",
      "B": "lacked sufficient funds",
      "C": "had too many vocal members",
      "D": "was dominated by hand-picked members."
    },
    "image_url": "",
    "image_cloudinary": "",
    "correct_answer": "D",
    "explanation": "click here",
    "explanation_image_url": "",
    "explanation_image_cloudinary": "",
    "url": "https://myschool.ng/classroom/history/32808",
    "passage": ""
  },
  {
    "id": 32809,
    "subject": "history",
    "exam_type": "JAMB",
    "exam_year": "2010",
    "question": "Two institutions of local government in Nigeria during the colonial period were native courts and",
    "options": {
      "A": "legislative council",
      "B": "regional treasury",
      "C": "native treasury",
      "D": "native police."
    },
    "image_url": "",
    "image_cloudinary": "",
    "correct_answer": "C",
    "explanation": "click here",
    "explanation_image_url": "",
    "explanation_image_cloudinary": "",
    "url": "https://myschool.ng/classroom/history/32809",
    "passage": ""
  },
  {
    "id": 32810,
    "subject": "history",
    "exam_type": "JAMB",
    "exam_year": "2010",
    "question": "Certain chiefs in Eastern Nigeria were called warrant chiefs because they",
    "options": {
      "A": "had some royal connections",
      "B": "were created by the British",
      "C": "had warrants to arrest offenders",
      "D": "were the first to receive Western education."
    },
    "image_url": "",
    "image_cloudinary": "",
    "correct_answer": "B",
    "explanation": "click here",
    "explanation_image_url": "",
    "explanation_image_cloudinary": "",
    "url": "https://myschool.ng/classroom/history/32810",
    "passage": ""
  },
  {
    "id": 32811,
    "subject": "history",
    "exam_type": "JAMB",
    "exam_year": "2010",
    "question": "In colonial Nigeria, mining industry was promoted in order to",
    "options": {
      "A": "diversify the economy",
      "B": "engage the railway system",
      "C": "make Nigeria self-reliant",
      "D": "maximize exploitation."
    },
    "image_url": "",
    "image_cloudinary": "",
    "correct_answer": "D",
    "explanation": "click here",
    "explanation_image_url": "",
    "explanation_image_cloudinary": "",
    "url": "https://myschool.ng/classroom/history/32811",
    "passage": ""
  },
  {
    "id": 32812,
    "subject": "history",
    "exam_type": "JAMB",
    "exam_year": "2010",
    "question": "The colonial government in Nigeria laid more emphasis on the production of export crops because",
    "options": {
      "A": "the people already had abundant food in stock",
      "B": "such crops were desperately needed abroad",
      "C": "such crops were more beneficial to the people",
      "D": "the soil was more suitable for the production of such crops."
    },
    "image_url": "",
    "image_cloudinary": "",
    "correct_answer": "B",
    "explanation": "click here",
    "explanation_image_url": "",
    "explanation_image_cloudinary": "",
    "url": "https://myschool.ng/classroom/history/32812",
    "passage": ""
  },
  {
    "id": 32813,
    "subject": "history",
    "exam_type": "JAMB",
    "exam_year": "2010",
    "question": "The Yaba Higher College did not meet the aspirations of the nationalists because",
    "options": {
      "A": "all its staff were Europeans",
      "B": "it was meant to train assistants to Europeans",
      "C": "only Europeans were qualified for admission",
      "D": "it was affiliated to a polytechnic in Europe."
    },
    "image_url": "",
    "image_cloudinary": "",
    "correct_answer": "B",
    "explanation": "click here",
    "explanation_image_url": "",
    "explanation_image_cloudinary": "",
    "url": "https://myschool.ng/classroom/history/32813",
    "passage": ""
  },
  {
    "id": 32815,
    "subject": "history",
    "exam_type": "JAMB",
    "exam_year": "2010",
    "question": "The 1922 Clifford Constitution restricted the franchise to",
    "options": {
      "A": "Calabar and Benin",
      "B": "Lagos and Calabar",
      "C": "Lagos and Warri",
      "D": "Warri and Lokoja"
    },
    "image_url": "",
    "image_cloudinary": "",
    "correct_answer": "B",
    "explanation": "click here",
    "explanation_image_url": "",
    "explanation_image_cloudinary": "",
    "url": "https://myschool.ng/classroom/history/32815",
    "passage": ""
  },
  {
    "id": 32816,
    "subject": "history",
    "exam_type": "JAMB",
    "exam_year": "2010",
    "question": "The political parties that formed the opposition during the First Republic in Nigeria were the",
    "options": {
      "A": "NCNC and AG",
      "B": "AG and UMBC",
      "C": "NCNC and NEPU",
      "D": "UMBC and NEPU."
    },
    "image_url": "",
    "image_cloudinary": "",
    "correct_answer": "A",
    "explanation": "The first party to assume the role of an opposition party was the Action Group (AG) led by Obafemi Awolowo in the first republic . The political intrigues during that era weakened the AG. All this happened shortly before the country's independence in 1959. The second opposition political party was the National Council of Nigeria and Cameroons (NCNC). The (NCNC) was led by Nnamdi Azikiwe.",
    "explanation_image_url": "",
    "explanation_image_cloudinary": "",
    "url": "https://myschool.ng/classroom/history/32816",
    "passage": ""
  },
  {
    "id": 32817,
    "subject": "history",
    "exam_type": "JAMB",
    "exam_year": "2010",
    "question": "The creation of Mid-Western region in 1963 was through",
    "options": {
      "A": "balloting",
      "B": "referendum",
      "C": "declaration",
      "D": "voting."
    },
    "image_url": "",
    "image_cloudinary": "",
    "correct_answer": "B",
    "explanation": "click here",
    "explanation_image_url": "",
    "explanation_image_cloudinary": "",
    "url": "https://myschool.ng/classroom/history/32817",
    "passage": ""
  },
  {
    "id": 32819,
    "subject": "history",
    "exam_type": "JAMB",
    "exam_year": "2010",
    "question": "The immediate cause of the January 1966 coup d’etat was",
    "options": {
      "A": "the breakdown of law and order in the West",
      "B": "the desire of the military to seize power",
      "C": "the failure of the 1963 census",
      "D": "interferance by foreign powers"
    },
    "image_url": "",
    "image_cloudinary": "",
    "correct_answer": "A",
    "explanation": "click here",
    "explanation_image_url": "",
    "explanation_image_cloudinary": "",
    "url": "https://myschool.ng/classroom/history/32819",
    "passage": ""
  },
  {
    "id": 32821,
    "subject": "history",
    "exam_type": "JAMB",
    "exam_year": "2010",
    "question": "Which of the following countries did the Murtala/Obasanjo regime assist during their struggle for independence?",
    "options": {
      "A": "Guinea Bissau and Namibia",
      "B": "Angola and Zimbabwe",
      "C": "Sierra Leone and Equitorial Guinea.",
      "D": "The Gambia and Tanzania"
    },
    "image_url": "",
    "image_cloudinary": "",
    "correct_answer": "B",
    "explanation": "click here",
    "explanation_image_url": "",
    "explanation_image_cloudinary": "",
    "url": "https://myschool.ng/classroom/history/32821",
    "passage": ""
  },
  {
    "id": 32823,
    "subject": "history",
    "exam_type": "JAMB",
    "exam_year": "2010",
    "question": "The Second Republic in Nigeria refers to\nthe period",
    "options": {
      "A": "General Babangida was Head of State",
      "B": "between 1979 and 1983",
      "C": "General Obasanjo was Head of State",
      "D": "the period between 1960 and 1966"
    },
    "image_url": "",
    "image_cloudinary": "",
    "correct_answer": "B",
    "explanation": "click here",
    "explanation_image_url": "",
    "explanation_image_cloudinary": "",
    "url": "https://myschool.ng/classroom/history/32823",
    "passage": ""
  },
  {
    "id": 32825,
    "subject": "history",
    "exam_type": "JAMB",
    "exam_year": "2010",
    "question": "Which of the following political parties\nformed an alliance in the Second\nRepublic?",
    "options": {
      "A": "UPN and NPN.",
      "B": "PRP and NPP.",
      "C": "NPN and NPP.",
      "D": "PRP and UPN."
    },
    "image_url": "",
    "image_cloudinary": "",
    "correct_answer": "C",
    "explanation": "click here",
    "explanation_image_url": "",
    "explanation_image_cloudinary": "",
    "url": "https://myschool.ng/classroom/history/32825",
    "passage": ""
  },
  {
    "id": 32827,
    "subject": "history",
    "exam_type": "JAMB",
    "exam_year": "2010",
    "question": "The political party that controlled the Federal Government during the Second Republic in Nigeria was the",
    "options": {
      "A": "Great Nigeria Peoples Party",
      "B": "Nigeria Peoples Party",
      "C": "Unity Party of Nigeria",
      "D": "National Party of Nigeria."
    },
    "image_url": "",
    "image_cloudinary": "",
    "correct_answer": "D",
    "explanation": "click here",
    "explanation_image_url": "",
    "explanation_image_cloudinary": "",
    "url": "https://myschool.ng/classroom/history/32827",
    "passage": ""
  },
  {
    "id": 32834,
    "subject": "history",
    "exam_type": "JAMB",
    "exam_year": "2010",
    "question": "The main aim of the formation of ECOMOG was to",
    "options": {
      "A": "foster stability in West Africa",
      "B": "solve boundary disputes among member states",
      "C": "provide security for the whole of Africa",
      "D": "tackle the problem of piracy in African seaways."
    },
    "image_url": "",
    "image_cloudinary": "",
    "correct_answer": "A",
    "explanation": "click here",
    "explanation_image_url": "",
    "explanation_image_cloudinary": "",
    "url": "https://myschool.ng/classroom/history/32834",
    "passage": ""
  },
  {
    "id": 32839,
    "subject": "history",
    "exam_type": "JAMB",
    "exam_year": "2010",
    "question": "A major contribution of Nigeria to\nECOWAS is in the area of",
    "options": {
      "A": "diplomacy",
      "B": "funding",
      "C": "military support",
      "D": "provision of education."
    },
    "image_url": "",
    "image_cloudinary": "",
    "correct_answer": "B",
    "explanation": "click here",
    "explanation_image_url": "",
    "explanation_image_cloudinary": "",
    "url": "https://myschool.ng/classroom/history/32839",
    "passage": ""
  },
  {
    "id": 32840,
    "subject": "history",
    "exam_type": "JAMB",
    "exam_year": "2010",
    "question": "Samori Toure is often described as the “African Napoleon” because he",
    "options": {
      "A": "was a great military tactician",
      "B": "learned a great deal from Napoleon",
      "C": "employed similar tactics as Napoleon",
      "D": "had a well trained army."
    },
    "image_url": "",
    "image_cloudinary": "",
    "correct_answer": "A",
    "explanation": "click here",
    "explanation_image_url": "",
    "explanation_image_cloudinary": "",
    "url": "https://myschool.ng/classroom/history/32840",
    "passage": ""
  },
  {
    "id": 32842,
    "subject": "history",
    "exam_type": "JAMB",
    "exam_year": "2010",
    "question": "A major similarity of the 19th century jihads in West Africa was that",
    "options": {
      "A": "they were executed at the same time",
      "B": "the participants were of the same origin",
      "C": "they had a common objective",
      "D": "they brought unity between the Hausa and the Fulani."
    },
    "image_url": "",
    "image_cloudinary": "",
    "correct_answer": "C",
    "explanation": "click here",
    "explanation_image_url": "",
    "explanation_image_cloudinary": "",
    "url": "https://myschool.ng/classroom/history/32842",
    "passage": ""
  },
  {
    "id": 32843,
    "subject": "history",
    "exam_type": "JAMB",
    "exam_year": "2010",
    "question": "The greatest contribution of the Christian Missionary Society in West Africa was in",
    "options": {
      "A": "establishing trading companies",
      "B": "stopping the slave trade",
      "C": "the emergence of educated elite",
      "D": "the production of cash crop."
    },
    "image_url": "",
    "image_cloudinary": "",
    "correct_answer": "C",
    "explanation": "click here",
    "explanation_image_url": "",
    "explanation_image_cloudinary": "",
    "url": "https://myschool.ng/classroom/history/32843",
    "passage": ""
  },
  {
    "id": 32844,
    "subject": "history",
    "exam_type": "JAMB",
    "exam_year": "2010",
    "question": "Egypt became the centre of international rivalry because of the",
    "options": {
      "A": "huge investment in the Suez-canal",
      "B": "rich soil for cotton and sugar cultivation",
      "C": "great cities of Cairo and Alexandria",
      "D": "strategic importance of the country."
    },
    "image_url": "",
    "image_cloudinary": "",
    "correct_answer": "D",
    "explanation": "click here",
    "explanation_image_url": "",
    "explanation_image_cloudinary": "",
    "url": "https://myschool.ng/classroom/history/32844",
    "passage": ""
  },
  {
    "id": 32846,
    "subject": "history",
    "exam_type": "JAMB",
    "exam_year": "2010",
    "question": "Muhammad es Sadek was a 19th century ruler of",
    "options": {
      "A": "Morocco",
      "B": "Libya",
      "C": "Tunisia",
      "D": "Algeria."
    },
    "image_url": "",
    "image_cloudinary": "",
    "correct_answer": "C",
    "explanation": "click here",
    "explanation_image_url": "",
    "explanation_image_cloudinary": "",
    "url": "https://myschool.ng/classroom/history/32846",
    "passage": ""
  },
  {
    "id": 32847,
    "subject": "history",
    "exam_type": "JAMB",
    "exam_year": "2010",
    "question": "Muhammad Ahmad was easily accepted as the Mahdi in the Sudan because",
    "options": {
      "A": "the Islamic leaders in the area did not live up to the expectations of the people",
      "B": "he came at a time the people were expecting to be delivered from the Egyptian rulers",
      "C": "the national army was not strong enough to defend the country",
      "D": "he was highly educated in the tenants of the Islamic religion."
    },
    "image_url": "",
    "image_cloudinary": "",
    "correct_answer": "B",
    "explanation": "click here",
    "explanation_image_url": "",
    "explanation_image_cloudinary": "",
    "url": "https://myschool.ng/classroom/history/32847",
    "passage": ""
  },
  {
    "id": 32848,
    "subject": "history",
    "exam_type": "JAMB",
    "exam_year": "2010",
    "question": "After leaving Oman for East Africa, Sayyid Said established his headquarters in",
    "options": {
      "A": "Zanzibar",
      "B": "Pemba",
      "C": "Mombasa",
      "D": "Kilwa."
    },
    "image_url": "",
    "image_cloudinary": "",
    "correct_answer": "A",
    "explanation": "click here",
    "explanation_image_url": "",
    "explanation_image_cloudinary": "",
    "url": "https://myschool.ng/classroom/history/32848",
    "passage": ""
  },
  {
    "id": 32849,
    "subject": "history",
    "exam_type": "JAMB",
    "exam_year": "2010",
    "question": "In 1887, a plot to depose Kabaka Mwanga was hatched by",
    "options": {
      "A": "a Muslim group",
      "B": "Baganda Christians",
      "C": "Arab slave merchants",
      "D": "Egyptian mercenaries."
    },
    "image_url": "",
    "image_cloudinary": "",
    "correct_answer": "A",
    "explanation": "click here",
    "explanation_image_url": "",
    "explanation_image_cloudinary": "",
    "url": "https://myschool.ng/classroom/history/32849",
    "passage": ""
  },
  {
    "id": 32850,
    "subject": "history",
    "exam_type": "JAMB",
    "exam_year": "2010",
    "question": "An Ethiopian monarch that committed suicide in a battle field was",
    "options": {
      "A": "Theodore II",
      "B": "Menelik",
      "C": "Johannes IV",
      "D": "Haile Selassie."
    },
    "image_url": "",
    "image_cloudinary": "",
    "correct_answer": "A",
    "explanation": "click here",
    "explanation_image_url": "",
    "explanation_image_cloudinary": "",
    "url": "https://myschool.ng/classroom/history/32850",
    "passage": ""
  },
  {
    "id": 32851,
    "subject": "history",
    "exam_type": "JAMB",
    "exam_year": "2010",
    "question": "The white settlers in Southern Africa were known as",
    "options": {
      "A": "Bantu",
      "B": "Boers",
      "C": "Bushmen",
      "D": "Hottentots."
    },
    "image_url": "",
    "image_cloudinary": "",
    "correct_answer": "B",
    "explanation": "click here",
    "explanation_image_url": "",
    "explanation_image_cloudinary": "",
    "url": "https://myschool.ng/classroom/history/32851",
    "passage": ""
  },
  {
    "id": 32852,
    "subject": "history",
    "exam_type": "JAMB",
    "exam_year": "2010",
    "question": "The Mfecane occured as a result of",
    "options": {
      "A": "long standing inter-group rivalry",
      "B": "inter-group struggles for natural resources",
      "C": "Ndwandwe’s domination of the Zulu",
      "D": "Shaka’s inordinate military ambition."
    },
    "image_url": "",
    "image_cloudinary": "",
    "correct_answer": "B",
    "explanation": "click here",
    "explanation_image_url": "",
    "explanation_image_cloudinary": "",
    "url": "https://myschool.ng/classroom/history/32852",
    "passage": ""
  },
  {
    "id": 32853,
    "subject": "history",
    "exam_type": "JAMB",
    "exam_year": "2010",
    "question": "The Fashoda incident of 1898 resulted in a rift between",
    "options": {
      "A": "France and Germany",
      "B": "Germany and Britain",
      "C": "France and Italy",
      "D": "Britain and France."
    },
    "image_url": "",
    "image_cloudinary": "",
    "correct_answer": "D",
    "explanation": "click here",
    "explanation_image_url": "",
    "explanation_image_cloudinary": "",
    "url": "https://myschool.ng/classroom/history/32853",
    "passage": ""
  },
  {
    "id": 32854,
    "subject": "history",
    "exam_type": "JAMB",
    "exam_year": "2010",
    "question": "Paternalism was a colonial policy adopted\nby",
    "options": {
      "A": "Britain",
      "B": "Portugal",
      "C": "Germany",
      "D": "France."
    },
    "image_url": "",
    "image_cloudinary": "",
    "correct_answer": "C",
    "explanation": "click here",
    "explanation_image_url": "",
    "explanation_image_cloudinary": "",
    "url": "https://myschool.ng/classroom/history/32854",
    "passage": ""
  },
  {
    "id": 32855,
    "subject": "history",
    "exam_type": "JAMB",
    "exam_year": "2010",
    "question": "Where was indirect rule practised before it was introduced to Africa?",
    "options": {
      "A": "India.",
      "B": "Malaysia.",
      "C": "Pakistan.",
      "D": "Indonesia."
    },
    "image_url": "",
    "image_cloudinary": "",
    "correct_answer": "A",
    "explanation": "click here",
    "explanation_image_url": "",
    "explanation_image_cloudinary": "",
    "url": "https://myschool.ng/classroom/history/32855",
    "passage": ""
  },
  {
    "id": 32856,
    "subject": "history",
    "exam_type": "JAMB",
    "exam_year": "2010",
    "question": "The indirect rule system of administration meant that the colonialists",
    "options": {
      "A": "ruled through native courts",
      "B": "barred the educated elite from local politics",
      "C": "ruled through traditional institutions",
      "D": "relied mostly on local interpreters"
    },
    "image_url": "",
    "image_cloudinary": "",
    "correct_answer": "C",
    "explanation": "click here",
    "explanation_image_url": "",
    "explanation_image_cloudinary": "",
    "url": "https://myschool.ng/classroom/history/32856",
    "passage": ""
  },
  {
    "id": 32857,
    "subject": "history",
    "exam_type": "JAMB",
    "exam_year": "2010",
    "question": "In post-apartheid South Africa, the main concern of government is to",
    "options": {
      "A": "punish the people who perpetrated apartheid",
      "B": "redress the injustices of the apartheid policy",
      "C": "make the country the giant of Africa",
      "D": "make the country a permanent member of the UN Security Council"
    },
    "image_url": "",
    "image_cloudinary": "",
    "correct_answer": "B",
    "explanation": "click here",
    "explanation_image_url": "",
    "explanation_image_cloudinary": "",
    "url": "https://myschool.ng/classroom/history/32857",
    "passage": ""
  },
  {
    "id": 32858,
    "subject": "history",
    "exam_type": "JAMB",
    "exam_year": "2010",
    "question": "The Ogaden war between Ethiopia and Somalia was caused by",
    "options": {
      "A": "disagreement over trade",
      "B": "refugee problems",
      "C": "boundary disputes",
      "D": "personality clash between their leaders"
    },
    "image_url": "",
    "image_cloudinary": "",
    "correct_answer": "C",
    "explanation": "click here",
    "explanation_image_url": "",
    "explanation_image_cloudinary": "",
    "url": "https://myschool.ng/classroom/history/32858",
    "passage": ""
  },
  {
    "id": 32860,
    "subject": "history",
    "exam_type": "JAMB",
    "exam_year": "2002",
    "question": "The ethnic groups that occupy the hinterland of the Bight of Benin include the",
    "options": {
      "A": "Edo, the Yoruba and the Urhobo",
      "B": "Itsekiri, the Igbo and the Idoma",
      "C": "Yoruba, the Jukun and the Efik",
      "D": "Igbo, the Ibibio and the Tiv"
    },
    "image_url": "",
    "image_cloudinary": "",
    "correct_answer": "A",
    "explanation": "",
    "explanation_image_url": "",
    "explanation_image_cloudinary": "",
    "url": "https://myschool.ng/classroom/history/32860",
    "passage": ""
  },
  {
    "id": 32861,
    "subject": "history",
    "exam_type": "JAMB",
    "exam_year": "2002",
    "question": "The Nok culture is associated with the archaelogical findings at",
    "options": {
      "A": "Ile-Ife",
      "B": "Benin",
      "C": "Taruga",
      "D": "Igbo Ukwu."
    },
    "image_url": "",
    "image_cloudinary": "",
    "correct_answer": "C",
    "explanation": "",
    "explanation_image_url": "",
    "explanation_image_cloudinary": "",
    "url": "https://myschool.ng/classroom/history/32861",
    "passage": ""
  },
  {
    "id": 32862,
    "subject": "history",
    "exam_type": "JAMB",
    "exam_year": "2002",
    "question": "In the pre-colonial period, the Aku of Wukari derived his power mainly from",
    "options": {
      "A": "the strength of his army",
      "B": "the role as a supplier of slaves",
      "C": "his control of trade routes",
      "D": "his spiritual influence in the kingdom."
    },
    "image_url": "",
    "image_cloudinary": "",
    "correct_answer": "D",
    "explanation": "click here",
    "explanation_image_url": "",
    "explanation_image_cloudinary": "",
    "url": "https://myschool.ng/classroom/history/32862",
    "passage": ""
  },
  {
    "id": 32863,
    "subject": "history",
    "exam_type": "JAMB",
    "exam_year": "2002",
    "question": "The last ruler of the Ogiso dynasty in the Benin Empire was",
    "options": {
      "A": "Oba Eweka",
      "B": "Oba Owodo",
      "C": "Oba Oranmiyan",
      "D": "Oba Ewuare."
    },
    "image_url": "",
    "image_cloudinary": "",
    "correct_answer": "B",
    "explanation": "",
    "explanation_image_url": "",
    "explanation_image_cloudinary": "",
    "url": "https://myschool.ng/classroom/history/32863",
    "passage": ""
  },
  {
    "id": 32864,
    "subject": "history",
    "exam_type": "JAMB",
    "exam_year": "2002",
    "question": "The Olu of Itsekiri was assisted in his administration by a council of chiefs\ncalled",
    "options": {
      "A": "Ogboni",
      "B": "Ekpako",
      "C": "Ekine",
      "D": "Ojoye."
    },
    "image_url": "",
    "image_cloudinary": "",
    "correct_answer": "D",
    "explanation": "click here",
    "explanation_image_url": "",
    "explanation_image_cloudinary": "",
    "url": "https://myschool.ng/classroom/history/32864",
    "passage": ""
  },
  {
    "id": 32865,
    "subject": "history",
    "exam_type": "JAMB",
    "exam_year": "2002",
    "question": "In pre-colonial Nigeria, the Nsibidi form of writing was found in the",
    "options": {
      "A": "Niger-Benue Confluence",
      "B": "Cross River Area",
      "C": "Niger Delta",
      "D": "Anambra River Valley."
    },
    "image_url": "",
    "image_cloudinary": "",
    "correct_answer": "B",
    "explanation": "",
    "explanation_image_url": "",
    "explanation_image_cloudinary": "",
    "url": "https://myschool.ng/classroom/history/32865",
    "passage": ""
  },
  {
    "id": 32866,
    "subject": "history",
    "exam_type": "JAMB",
    "exam_year": "2002",
    "question": "The Bayajidda tradition suggests that",
    "options": {
      "A": "Hausa ancestors came from Arabia",
      "B": "women exercised political power in pre-Islamic Hausaland",
      "C": "the introduction of Islam led to the formation of the Hausa city states",
      "D": "The Queen of Daura was the first to embrace Islam."
    },
    "image_url": "",
    "image_cloudinary": "",
    "correct_answer": "B",
    "explanation": "",
    "explanation_image_url": "",
    "explanation_image_cloudinary": "",
    "url": "https://myschool.ng/classroom/history/32866",
    "passage": ""
  },
  {
    "id": 32867,
    "subject": "history",
    "exam_type": "JAMB",
    "exam_year": "2002",
    "question": "Which of the following rulers of Kano promoted Islam to a state religion?",
    "options": {
      "A": "Kanajeji",
      "B": "Rumfa",
      "C": "Yaji",
      "D": "Abdullahi"
    },
    "image_url": "",
    "image_cloudinary": "",
    "correct_answer": "B",
    "explanation": "click here",
    "explanation_image_url": "",
    "explanation_image_cloudinary": "",
    "url": "https://myschool.ng/classroom/history/32867",
    "passage": ""
  },
  {
    "id": 32868,
    "subject": "history",
    "exam_type": "JAMB",
    "exam_year": "2002",
    "question": "The correspondence between Sokoto and Borno during the jihad was entered on the",
    "options": {
      "A": "qualification for a true Muslin to perform the hajj",
      "B": "justification of the jihad against an Islamic state",
      "C": "declaration of the jihad against non-Muslims",
      "D": "difference between traditional religion and Islam."
    },
    "image_url": "",
    "image_cloudinary": "",
    "correct_answer": "B",
    "explanation": "click here",
    "explanation_image_url": "",
    "explanation_image_cloudinary": "",
    "url": "https://myschool.ng/classroom/history/32868",
    "passage": ""
  },
  {
    "id": 32869,
    "subject": "history",
    "exam_type": "JAMB",
    "exam_year": "2002",
    "question": "The most powerful states that emerged after the fall of the Old Oyo were",
    "options": {
      "A": "Owu and Abeokuta",
      "B": "Ijaiye and Ife",
      "C": "Ibadan and Ijaiye",
      "D": "New Oyo and Ibadan."
    },
    "image_url": "",
    "image_cloudinary": "",
    "correct_answer": "A",
    "explanation": "",
    "explanation_image_url": "",
    "explanation_image_cloudinary": "",
    "url": "https://myschool.ng/classroom/history/32869",
    "passage": ""
  },
  {
    "id": 32870,
    "subject": "history",
    "exam_type": "JAMB",
    "exam_year": "2002",
    "question": "Which of the following areas did Malam Alimi incorporate into the Sokoto Caliphate?",
    "options": {
      "A": "Bida",
      "B": "Ilorin",
      "C": "Adamawa",
      "D": "Bauchi"
    },
    "image_url": "",
    "image_cloudinary": "",
    "correct_answer": "C",
    "explanation": "click here",
    "explanation_image_url": "",
    "explanation_image_cloudinary": "",
    "url": "https://myschool.ng/classroom/history/32870",
    "passage": ""
  },
  {
    "id": 32871,
    "subject": "history",
    "exam_type": "JAMB",
    "exam_year": "2002",
    "question": "The 1886 Treaty is significant in Yoruba history because it",
    "options": {
      "A": "brought peace and stability to Yorubaland",
      "B": "affirmed Ekitiparapo’s independence",
      "C": "was negotiated by two Yoruba repatriates",
      "D": "reopened trade between Lagos and the hinterland."
    },
    "image_url": "",
    "image_cloudinary": "",
    "correct_answer": "A",
    "explanation": "click here",
    "explanation_image_url": "",
    "explanation_image_cloudinary": "",
    "url": "https://myschool.ng/classroom/history/32871",
    "passage": ""
  },
  {
    "id": 32872,
    "subject": "history",
    "exam_type": "JAMB",
    "exam_year": "2002",
    "question": "Intensified European activity along the coast in the nineteenth century led Benin to",
    "options": {
      "A": "redirect her trade to the north",
      "B": "lose control of some vassal states",
      "C": "expel Christian missionaries",
      "D": "embark on a cultural revival in the area."
    },
    "image_url": "",
    "image_cloudinary": "",
    "correct_answer": "B",
    "explanation": "click here",
    "explanation_image_url": "",
    "explanation_image_cloudinary": "",
    "url": "https://myschool.ng/classroom/history/32872",
    "passage": ""
  },
  {
    "id": 32880,
    "subject": "history",
    "exam_type": "JAMB",
    "exam_year": "2002",
    "question": "It was difficult for the Nigerian coastal chiefs to give up the slave trade after its abolition because",
    "options": {
      "A": "it had been part of African culture",
      "B": "Africans were too involved to give up the trade",
      "C": "the British Navy was not effective in enforcing the abolition",
      "D": "the trade was still crucial to the economy of their states."
    },
    "image_url": "",
    "image_cloudinary": "",
    "correct_answer": "D",
    "explanation": "",
    "explanation_image_url": "",
    "explanation_image_cloudinary": "",
    "url": "https://myschool.ng/classroom/history/32880",
    "passage": ""
  },
  {
    "id": 32881,
    "subject": "history",
    "exam_type": "JAMB",
    "exam_year": "2002",
    "question": "The ruler that was driven out of Lagos by the British was",
    "options": {
      "A": "Oba Akintoye",
      "B": "Oba Dosumu",
      "C": "Oba Kosoko",
      "D": "Oba Adele."
    },
    "image_url": "",
    "image_cloudinary": "",
    "correct_answer": "C",
    "explanation": "",
    "explanation_image_url": "",
    "explanation_image_cloudinary": "",
    "url": "https://myschool.ng/classroom/history/32881",
    "passage": ""
  },
  {
    "id": 32882,
    "subject": "history",
    "exam_type": "JAMB",
    "exam_year": "2002",
    "question": "Which of the following played the greatest role in the British conquest of Nigeria?",
    "options": {
      "A": "The John Holt Company",
      "B": "The Royal Niger Company",
      "C": "The Church Missionary Society",
      "D": "The Roman Catholic Mission."
    },
    "image_url": "",
    "image_cloudinary": "",
    "correct_answer": "B",
    "explanation": "",
    "explanation_image_url": "",
    "explanation_image_cloudinary": "",
    "url": "https://myschool.ng/classroom/history/32882",
    "passage": ""
  },
  {
    "id": 32883,
    "subject": "history",
    "exam_type": "JAMB",
    "exam_year": "2002",
    "question": "Chief Agho Obaseki is remembered is Benin history because",
    "options": {
      "A": "he collaborated with the British to suppress the monarchy",
      "B": "he was regarded as a true patriot",
      "C": "he played an important role in the restoration of the monarchy",
      "D": "Oba Aguobasimi delegated a lot of powers to him."
    },
    "image_url": "",
    "image_cloudinary": "",
    "correct_answer": "A",
    "explanation": "click here",
    "explanation_image_url": "",
    "explanation_image_cloudinary": "",
    "url": "https://myschool.ng/classroom/history/32883",
    "passage": ""
  },
  {
    "id": 32884,
    "subject": "history",
    "exam_type": "JAMB",
    "exam_year": "2002",
    "question": "An influential advocate of the amalgamation of the Northern and Southern Protectorates was",
    "options": {
      "A": "E.D. morel",
      "B": "Otunba Payne",
      "C": "John Beecroft",
      "D": "Henry Carr"
    },
    "image_url": "",
    "image_cloudinary": "",
    "correct_answer": "A",
    "explanation": "",
    "explanation_image_url": "",
    "explanation_image_cloudinary": "",
    "url": "https://myschool.ng/classroom/history/32884",
    "passage": ""
  },
  {
    "id": 32885,
    "subject": "history",
    "exam_type": "JAMB",
    "exam_year": "2002",
    "question": "The Native Authority Ordinance of 1916 introduced direct taxation into Yorubaland and thereby",
    "options": {
      "A": "gave greater administrative and judicial responsibilities to the Oba",
      "B": "made Yorubaland a beneficiary of British aid",
      "C": "encouraged the appointment of more British officials",
      "D": "involved the educated elite in colonial administration."
    },
    "image_url": "",
    "image_cloudinary": "",
    "correct_answer": "A",
    "explanation": "click here",
    "explanation_image_url": "",
    "explanation_image_cloudinary": "",
    "url": "https://myschool.ng/classroom/history/32885",
    "passage": ""
  },
  {
    "id": 32886,
    "subject": "history",
    "exam_type": "JAMB",
    "exam_year": "2002",
    "question": "The colonial officer who was responsible for splitting the Southern Province in to Eastern and Western Provinces was",
    "options": {
      "A": "Bernard Bourdillon",
      "B": "Graeme Thompson",
      "C": "Hugh Clifford",
      "D": "Frederick Lugard."
    },
    "image_url": "",
    "image_cloudinary": "",
    "correct_answer": "A",
    "explanation": "",
    "explanation_image_url": "",
    "explanation_image_cloudinary": "",
    "url": "https://myschool.ng/classroom/history/32886",
    "passage": ""
  },
  {
    "id": 32887,
    "subject": "history",
    "exam_type": "JAMB",
    "exam_year": "2002",
    "question": "The 1945 General Strike was led by",
    "options": {
      "A": "Herbert Macaulay",
      "B": "Michael Imoudu",
      "C": "Wahab Goodluck",
      "D": "Olufunmilayo Ransome-Kuti."
    },
    "image_url": "",
    "image_cloudinary": "",
    "correct_answer": "B",
    "explanation": "",
    "explanation_image_url": "",
    "explanation_image_cloudinary": "",
    "url": "https://myschool.ng/classroom/history/32887",
    "passage": ""
  },
  {
    "id": 32888,
    "subject": "history",
    "exam_type": "JAMB",
    "exam_year": "2002",
    "question": "The objective of the 1934 legislation imposing quotas on imported goods from non-British sources was to",
    "options": {
      "A": "develop Nigerian industries",
      "B": "increase Nigeria’s Gross National Product",
      "C": "exclude cheap Japanese textiles",
      "D": "regulate trade between Nigeria and other countries."
    },
    "image_url": "",
    "image_cloudinary": "",
    "correct_answer": "C",
    "explanation": "click here",
    "explanation_image_url": "",
    "explanation_image_cloudinary": "",
    "url": "https://myschool.ng/classroom/history/32888",
    "passage": ""
  },
  {
    "id": 32889,
    "subject": "history",
    "exam_type": "JAMB",
    "exam_year": "2002",
    "question": "The Tin Producers’ Association was formed in 1929 to",
    "options": {
      "A": "increase the production of tin",
      "B": "alleviate the hardship of miners",
      "C": "regulate the supply of tin",
      "D": "introduce modern methods of production."
    },
    "image_url": "",
    "image_cloudinary": "",
    "correct_answer": "C",
    "explanation": "",
    "explanation_image_url": "",
    "explanation_image_cloudinary": "",
    "url": "https://myschool.ng/classroom/history/32889",
    "passage": ""
  },
  {
    "id": 32890,
    "subject": "history",
    "exam_type": "JAMB",
    "exam_year": "2002",
    "question": "One major inadequacy of the Richards Constitution was that",
    "options": {
      "A": "it was introduced without due and exhaustive consultations",
      "B": "the official members of the legislature were too many",
      "C": "it could not solve Nigeria’s economic and social problems",
      "D": "it did not cater for the interest of the minorities."
    },
    "image_url": "",
    "image_cloudinary": "",
    "correct_answer": "A",
    "explanation": "click here",
    "explanation_image_url": "",
    "explanation_image_cloudinary": "",
    "url": "https://myschool.ng/classroom/history/32890",
    "passage": ""
  },
  {
    "id": 32891,
    "subject": "history",
    "exam_type": "JAMB",
    "exam_year": "2002",
    "question": "A major recommendation of the Henry Willink Commission was the",
    "options": {
      "A": "protection of special interests",
      "B": "creation of more administrative units",
      "C": "inclusion of a bill of rights in the 1960 Constitution",
      "D": "need to ensure the educational rights of the people."
    },
    "image_url": "",
    "image_cloudinary": "",
    "correct_answer": "C",
    "explanation": "click here",
    "explanation_image_url": "",
    "explanation_image_cloudinary": "",
    "url": "https://myschool.ng/classroom/history/32891",
    "passage": ""
  },
  {
    "id": 32892,
    "subject": "history",
    "exam_type": "JAMB",
    "exam_year": "2002",
    "question": "The political party with the most radical orientation in the First Republic was the",
    "options": {
      "A": "NEPU",
      "B": "NPC",
      "C": "NCNC",
      "D": "AG."
    },
    "image_url": "",
    "image_cloudinary": "",
    "correct_answer": "A",
    "explanation": "",
    "explanation_image_url": "",
    "explanation_image_cloudinary": "",
    "url": "https://myschool.ng/classroom/history/32892",
    "passage": ""
  },
  {
    "id": 32893,
    "subject": "history",
    "exam_type": "JAMB",
    "exam_year": "2002",
    "question": "The Premier of the Eastern Region of Nigeria in 1962 was",
    "options": {
      "A": "Chief Michael Okpara",
      "B": "Dr. Nnamdi Azikiwe",
      "C": "Dr. Akanu Ibiam",
      "D": "Mr. Ukpabi Asika."
    },
    "image_url": "",
    "image_cloudinary": "",
    "correct_answer": "A",
    "explanation": "",
    "explanation_image_url": "",
    "explanation_image_cloudinary": "",
    "url": "https://myschool.ng/classroom/history/32893",
    "passage": ""
  }
]