[
  {
    "id": 48067,
    "subject": "music",
    "exam_type": "JAMB",
    "exam_year": "2018",
    "question": "kwaa Mensah was the leader of the",
    "options": {
      "A": "Fanti Trio",
      "B": "Accra Orchestra",
      "C": "Ghana Combo",
      "D": "Jazz Kings"
    },
    "image_url": "",
    "image_cloudinary": "",
    "correct_answer": "A",
    "explanation": "click here",
    "explanation_image_url": "",
    "explanation_image_cloudinary": "",
    "url": "https://myschool.ng/classroom/music/48067",
    "passage": ""
  },
  {
    "id": 48068,
    "subject": "music",
    "exam_type": "JAMB",
    "exam_year": "2018",
    "question": "Which of the following wrote compositions using the atonal style?",
    "options": {
      "A": "Stravinsky",
      "B": "Schoenberg",
      "C": "Schubert",
      "D": "Smetana"
    },
    "image_url": "",
    "image_cloudinary": "",
    "correct_answer": "B",
    "explanation": "click here",
    "explanation_image_url": "",
    "explanation_image_cloudinary": "",
    "url": "https://myschool.ng/classroom/music/48068",
    "passage": ""
  },
  {
    "id": 48069,
    "subject": "music",
    "exam_type": "JAMB",
    "exam_year": "2018",
    "question": "The italian term pizzicato means",
    "options": {
      "A": "pointed",
      "B": "plucked",
      "C": "pushed",
      "D": "painted"
    },
    "image_url": "",
    "image_cloudinary": "",
    "correct_answer": "B",
    "explanation": "click here",
    "explanation_image_url": "",
    "explanation_image_cloudinary": "",
    "url": "https://myschool.ng/classroom/music/48069",
    "passage": ""
  }
]